Workbook

Sheet Solitario
B1: Rasgos | C1: Niñez | D1: Adolescencia | E1: Juventud | F1: Vejez
A2: 1 | B2: Tienen muy poca energía. | D2: No | E2: No
A3: 2 | B3: Son negativos y pesimistas. | D3: No | E3: No
A4: 3 | B4: Carecen del deseo de cambiar algo o de la energía para hacerlo o de ambas. | D4: No | E4: No
A5: 4 | B5: Cuando tienen un objetivo son persistentes. Pueden ser genios. | D5: Si | E5: Si
A6: 5 | B6: Prácticos, fríos, obsesivos y perfeccionistas. | D6: No | E6: No
A7: 6 | B7: Disfrutan la soledad y el silencio más que ningún otro tipo; pero no son tímidos. | D7: Si | E7: Si | G7: ?????
A8: 7 | B8: Independientes. Observadores. | D8: No | E8: No
A9: 8 | B9: En reuniones tienden a aislarse. Introvertidos. Privados. | D9: No | E9: No
A10: 9 | B10: Son distantes e inexpresivos pero de emociones muy profundas y subterráneas. | D10: No | E10: No
A11: 10 | B11: Saben escuchar, son pacientes. | D11: No | E11: No
A12: 11 | B12: Profesionales de los puntos negros, aunque ellos se consideran “realistas”. | D12: No | E12: No
A13: 12 | B13: Sienten predilección por lugares apartados, fríos y oscuros. | D13: No | E13: No
A14: 13 | B14: Necesitan a quién desobedecer, rechazar o ignorar. | D14: No | E14: No
A15: 14 | B15: Tienen pocos amigos pero muy buenos. | D15: No | E15: No
A16: 15 | B16: Casi no necesitan la aprobación de los demás. | D16: No | E16: No
A17: 16 | B17: Selectivos, sinceros, genuinos y fieles a la causa. Discretos. | D17: Si | E17: Si
A18: 17 | B18: Son de trato difícil por sus emociones inestables. | D18: No | E18: No
A19: 18 | B19: Son posesivos y avaros. Acumulativos; coleccionan cosas pequeñas. | D19: No | E19: No
A20: 19 | B20: Imaginativos y de temperamento artístico. | D20: Si | E20: Si | G20: Emocional???
A21: 20 | B21: Tienen raro sentido del humor. Son conservadores. | D21: No | E21: No
A22: 21 | B22: Suelen vestir de colores oscuros u opacos. | D22: No | E22: No
A23: 22 | B23: Son buenos archivistas, bibliotecarios, contadores, financieros, administradores. | D23: No | E23: No
A24: 23 | B24: Confiables con números y libros. Excelentes en ocupaciones que requieran precisión y atención minuciosa. | D24: No | E24: No
B25: Porcentaje | C25: =COUNTIF(C2:C24,"si")/$A$24 -> 0 | D25: =COUNTIF(D2:D24,"Si")/$A$24 -> 0.17391304 | E25: =COUNTIF(E2:E24,"si")/$A$24 -> 0.17391304 | F25: =COUNTIF(F2:F24,"si")/$A$24 -> 0

Sheet Sensitivo
B1: Rasgos | C1: Niñez | D1: Adolescencia | E1: Juventud | F1: Vejez
A2: 1 | B2: Son el tipo que genera menos energía. Tienen el metabolismo más lento. | D2: No | E2: No
A3: 2 | B3: Son optimistas y positivos. | D3: No | E3: No
A4: 3 | B4: No tienen determinación. | D4: Si | E4: Si
A5: 4 | B5: Nunca andan solos. Buscan calor y energía en otras personas. | D5: Si | E5: Si
A6: 5 | B6: Son muy desordenados. Duermen mucho. Son friolentos. | D6: Si | E6: Si
A7: 6 | B7: No pueden discernir ni decidir. Aceptan todo y a todos. | D7: No | E7: No
A8: 7 | B8: Menosprecian sus propias opiniones. | D8: No | E8: No
A9: 8 | B9: Dan todo sin esperar nada a cambio, más que compañía. | D9: Si | E9: Si
A10: 9 | B10: Son amantes intuitivos, muy sensibles y sensuales. | D10: Si | E10: Si
A11: 10 | B11: Gozan intensamente de la naturaleza. | D11: Si | E11: Si
A12: 11 | B12: Extraordinariamente sensitivos. | D12: Si | E12: Si
A13: 12 | B13: Tienen buena comunicación con plantas, animales y niños. | D13: Si | E13: Si
... A23: 22 | B23: Excelentes en ocupaciones que requieran contacto humano de manera reposada y armónica. | D23: Si | E23: Si
B24: Porcentaje | C24: =COUNTIF(C2:C23,"si")/$A$23 -> 0 | D24: =COUNTIF(D2:D23,"si")/$A$23 -> 0.59090909 | E24: =COUNTIF(E2:E23,"si")/$A$23 -> 0.59090909 | F24: =COUNTIF(F2:F23,"si")/$A$23 -> 0

Sheet Agudo
B1: Rasgos | C1: Niñez | D1: Adolescencia | E1: Juventud | F1: Vejez
A2: 1 | B2: Tienen exceso de energía, difícil de contener en su cuerpo reducido. | D2: Si | E2: Si | G2: Importante
A3: 2 | B3: Son muy inquietos y rápidos. Actividad de tipo nervioso. | D3: Si | E3: Si
A4: 3 | B4: Tienen una gran rapidez intelectual. Piensan en zig zag. Son muy agudos. | D4: Si | E4: Si
A5: 4 | B5: Enredados, no dicen las cosas de manera clara y directa. | D5: Si | E5: Si
A6: 5 | B6: Intrigosos, astutos y manipuladores. | D6: No | E6: No
A7: 6 | B7: Son buenos para hacer dinero. Emprendedores. | D7: Si | E7: Si
A8: 7 | B8: Se involucran simultáneamente en muchos proyectos que suelen embrollar. | D8: Si | E8: Si
A9: 8 | B9: Buscan ser el centro de atención. Son envidiosos y competitivos: siempre quieren ganar. | D9: Si | E9: Si
A10: 9 | B10: Si se sienten acorralados, se hacen las víctimas. Se justifican, no aceptan sus equivocaciones. | D10: Si | E10: Si
A11: 10 | B11: Divertidos anfitriones. Efectistas para vestirse. | D11: Si | E11: Si
A12: 11 | B12: Necesitan la admiración de los otros, más que ninguno. Son desconfiados y mitómanos. | D12: Si | E12: Si
A13: 12 | B13: No soportan ser ignorados. Tienden a la hipocondría. | D13: Si | E13: Si
A14: 13 | B14: Pecados menores: cleptomanía. | D14: Si | E14: Si
... A18: 17 | B18: Tienen una gran capacidad para gozar la vida. Gran sentido del humor. | D18: Si | E18: Si
A19: 18 | B19: Actúan por interés propio y creen que así son los demás. | D19: No | E19: No | G19: Importante
A20: 19 | B20: Les gusta conocer las reglas para romperlas. | D20: No | E20: No
A21: 20 | B21: Se realizan al encontrar rebajas. | D21: Si | E21: Si
A22: 21 | B22: Muy creativos. Líderes verborreicos: se escuchan cuando hablan. | D22: Si | E22: Si
A23: 22 | B23: Son vendedores natos. Buenos políticos, comediantes, detectives, fiscalistas, imitadores. | D23: Si | E23: SI
A24: 23 | B24: Excelentes en ocupaciones que requieran de gran movilidad y dinamismo, de rapidez tanto física como mental. | D24: Si | E24: Si
B25: Porcentaje | C25: =COUNTIF(C2:C24,"si")/$A$24 -> 0 | D25: =COUNTIF(D2:D24,"si")/$A$24 -> 0.82608696 | E25: =COUNTIF(E2:E24,"si")/$A$24 -> 0.82608696 | F25: =COUNTIF(F2:F24,"si")/$A$24 -> 0
G26: Eres un agudo de catalogo.

Sheet Estructurado
B1: Rasgos | C1: Niñez | D1: Adolescencia | E1: Juventud | F1: Vejez
A2: 1 | B2: Tienen mucha energía pero son pausados, metódicos, tranquilos. | D2: Si | E2: Si
A3: 2 | B3: Son racionales, moderados y objetivos. | D3: Si | E3: Si
A4: 3 | B4: Gran capacidad analítica. Buscan la verdad. | D4: SI | E4: Si
A5: 4 | B5: Excesivamente lógicos, fríos y estructurados. Didácticos hasta la exasperación. | D5: No | E5: No
A6: 5 | B6: Para ellos no hay nada trivial. Amplia visión. | D6: Si | E6: Si | G6: Profundo: penasmientos, ideas
A7: 6 | B7: Les gusta acumular datos. Investigan el origen de las cosas. | D7: Si | E7: Si
A8: 7 | B8: Buscan claridad y síntesis en sus vidas. Les fascinan las estadísticas. | D8: No | E8: No
A9: 8 | B9: Son soberbios, inflexibles y arrogantes. | D9: Si | E9: Si
A10: 9 | B10: No concretan. Planean en exceso. | D10: Si | E10: Si
A11: 10 | B11: Son perfeccionistas. Sumamente ordenados. | D11: Si | E11: Si
A12: 11 | B12: Son rutinarios, monótonos, predecibles. | D12: Si | E12: Si
A13: 12 | B13: Cuando algo les gusta lo repiten e incorporan a sus vidas. | D13: Si | E13: Si
A14: 13 | B14: Establecen jerarquías. Clasifican a las personas y a las cosas. | D14: Si | E14: Si
A15: 14 | B15: Son pedantes. Poco emotivos. Solemnes. | D15: No | E15: No
A16: 15 | B16: Tienen un gran sentido de la justicia. | D16: No | E16: No
A17: 16 | B17: Son paternalistas, excesivamente responsables. Incluso suelen asumir responsabilidades ajenas. | D17: Si | E17: Si
A18: 17 | B18: Grandes líderes por convencimiento. Extrovertidos y públicos. | D18: Si | E18: Si
... A24: 23 | B24: Excelentes en ocupaciones que requieran planeación analítica, investigación académica y comunicación estructurada. | D24: No | E24: No
B25: Porcentaje | C25: =COUNTIF(C2:C24,"si")/$A$24 -> 0 | D25: =COUNTIF(D2:D24,"si")/$A$24 -> 0.65217391 | E25: =COUNTIF(E2:E24,"si")/$A$24 -> 0.65217391 | F25: =COUNTIF(F2:F24,"si")/$A$24 -> 0

Sheet Energético
B1: Rasgos | C1: Niñez | D1: Adolescencia | E1: Juventud | F1: Vejez
A2: 1 | B2: Tienen gran vitalidad. Hiperactivos. Duermen poco. | D2: Si | E2: Si
A3: 2 | B3: Son competitivos, necios, bruscos en ademanes y palabras. | D3: No | E3: No
A4: 3 | B4: Son grandes hacedores. En cada proyecto se entregan hasta concretarlo. | D4: No | E4: No
A5: 4 | B5: Son líderes impositivos y beligerantes. | D5: No | E5: No
A6: 5 | B6: Constantemente buscan la acción que les permita liberar su enorme energía. | D6: No | E6: No
A7: 6 | B7: La impaciencia los lleva a no saber delegar. Se precipitan. | D7: Si | E7: Si
A8: 7 | B8: Imparten órdenes a diestra y siniestra. Prefieren que los obedezcan a que los amen. | D8: No | E8: No
A9: 8 | B9: Tienen un gran sentido práctico. Buenos estrategas. | D9: Si | E9: Si
A10: 9 | B10: Todo es URGENTE. Lo que les concierne lo exigen para ayer. | D10: Si | E10: Si
A11: 10 | B11: Creen en aquello que se les puede demostrar. Son tercos y escépticos. | D11: No | E11: No
A12: 11 | B12: Son fácilmente irritables, agresivos y dominantes. | D12: No | E12: No | G12: ¿Por qué?
A13: 12 | B13: Si no encuentran cómo canalizar su energía, se autodestruyen. | D13: Si | E13: Si | G13: No se pueden estar quietos porque tienen mucha energia.
A14: 13 | B14: Son leales, nobles y apasionados. Saben perdonar. Solo tienen amigos o enemigos. | D14: Si | E14: Si
A15: 14 | B15: Piden y dan verdades directas y brutalmente. Son MUY celosos. | D15: No | E15: No
A16: 15 | B16: Buscan tener retos que vencer. Se fijan metas y van de una en otra. | D16: No | E16: No
A17: 16 | B17: Buscan su libertad y les gustan los espacios abiertos. | D17: Si | E17: Si
A18: 17 | B18: El peligro los excita. Viven al filo de la navaja. Son rebeldes, no soportan la autoridad. | D18: Si | E18: Si
A19: 18 | B19: No planean. Van directo a la acción. Son impulsivos. | D19: No | E19: No
A20: 19 | B20: Las depresiones pueden encadenarlos a vicios. | D20: No | E20: No
A21: 20 | B21: Exagerados. No tienen límites, todo es a lo grande. | D21: Si | E21: Si | G21: Ejemplos
A22: 21 | B22: No les gustan las sutilezas. No soportan la traición. Son tímidos. | D22: No | E22: No
A23: 22 | B23: Buenos empresarios, políticos, deportistas, militares, comerciantes, organizadores. | D23: No | E23: No
A24: 23 | B24: Excelentes en ocupaciones que requieran capacidad de mando, visión práctica y resultados inmediatos. | D24: No | E24: No
B25: Porcentaje | C25: =COUNTIF(C2:C24,"si")/$A$24 -> 0 | D25: =COUNTIF(D2:D24,"si")/$A$24 -> 0.39130435 | E25: =COUNTIF(E2:E24,"si")/$A$24 -> 0.39130435 | F25: =COUNTIF(F2:F24,"si")/$A$24 -> 0

Sheet Expansivo
B1: Rasgos | C1: Niñez | D1: Adolescencia | E1: Juventud | F1: Vejez
A2: 1 | B2: Tienen poca energía. | D2: No | E2: No
A3: 2 | B3: Son dispersos, atolondrados y entusiastas. | D3: Si | E3: Si
A4: 3 | B4: Hacen mil cosas y no concretan ninguna, pero gozan todas. | D4: No | E4: No
A5: 4 | B5: Excéntricos, alegres, amigueros, les encantan las fiestas y reuniones. | D5: Si | E5: Si
A6: 5 | B6: Grandes Gourmets: su fascinación es la comida. | D6: No | E6: No
A7: 6 | B7: Excelentes anfitriones. Maternales. Apapachones. | D7: Si | E7: Si
A8: 7 | B8: Coleccionan amigos y cosas raras. Sus vestimentas suelen ser estrafalarias. | D8: Si | E8: Si
A9: 8 | B9: Despilfarradores. Muy generosos. Lo dan todo y más. | D9: Si | E9: Si
A10: 9 | B10: Son los que más sufren con el dolor ajeno. | D10: No | E10: No
A11: 10 | B11: Sus casas son de puertas abiertas. Hospedan a menesterosos. | D11: No | E11: No
A12: 11 | B12: Son populares. Quieren y se dan a querer de inmediato. | D12: Si | E12: Si
A13: 12 | B13: Requieren de la aceptación de los demás para vivir. No soportan el rechazo. | D13: Si | E13: Si
... A15: 14 | B15: Castigan con el látigo de su desprecio. | D15: No | E15: No
A16: 15 | B16: Optimistas. Se sienten comprometidos a mostrar su felicidad. | D16: Si | E16: Si | G16: No lo veo
A17: 16 | B17: Les encanta conciliar afectivamente. | D17: Si | E17: Si
A18: 17 | B18: Sentimentaloides, manipuladores, prolíficos. Ríen y lloran con facilidad. | D18: No | E18: No
A19: 18 | B19: Tienen aptitud para las lenguas. | D19: No | E19: No
A20: 19 | B20: Grandes chefs, artistas, locutores, médicos, traductores, diplomáticos, magos de las relaciones públicas. | D20: Si | E20: Si
A21: 20 | B21: Excelentes en ocupaciones que requieran trato social, espíritu de servicio y convivencia entusiasta. | D21: Si | E21: Si
B22: Porcentaje | C22: =COUNTIF(C2:C21,"si")/$A$21 -> 0 | D22: =COUNTIF(D2:D21,"si")/$A$21 -> 0.6 | E22: =COUNTIF(E2:E21,"si")/$A$21 -> 0.6 | F22: =COUNTIF(F2:F21,"si")/$A$21 -> 0

Sheet Carismático
B1: Rasgos | C1: Niñez | D1: Adolescencia | E1: Juventud | F1: Vejez
A2: 1 | B2: Constituyen el tipo más energético de todo el Heptagrama. | D2: No | E2: No
A3: 2 | B3: Tienen el metabolismo más rápido. | D3: No | E3: No
A4: 3 | B4: Procesan muchísima energía. Es difícil seguirles el paso. | D4: No | E4: No
A5: 4 | B5: Gran magnetismo. Irradian ternura, son muy intensos. | D5: Si | E5: Si | G5: Emocional?
A6: 5 | B6: Tienen polaridad universal. Extraordinaria energía sexual. | D6: No | E6: No
A7: 6 | B7: Volátil, ligero, eléctrico y veloz. | D7: No | E7: No
A8: 7 | B8: Gesticulan mucho al hablar y danzan al caminar. | D8: Si | E8: Si
A9: 8 | B9: Carismáticos, creativos, idealistas. | D9: Si | E9: Si | G9: Agudo
A10: 9 | B10: Contagian alegría y buen humor. | D10: Si | E10: Si | G10: Agudo
A11: 10 | B11: Estimulan los aspectos activos y positivos de los demás tipos. | D11: No | E11: No
A12: 11 | B12: Ingenuos, optimistas irracionales, entusiastas. | D12: Si | E12: Si
A13: 12 | B13: Suelen no ver el lado oscuro o negativo de las cosas o las personas. | D13: No | E13: No
A14: 13 | B14: Tienen grandes proyectos. Son dispersos. | D14: Si | E14: Si
A15: 14 | B15: Ven el lado positivo en todo. Son muy adaptables. | D15: No | E15: No
A16: 15 | B16: Visionarios. No tienen los pies en la tierra. | D16: Si | E16: Si
A17: 16 | B17: Dan lo mejor de sí mismos. Son serviciales. | D17: No | E17: No
A18: 17 | B18: Son amigables pero no tienen amigos. | D18: No | E18: No
A19: 18 | B19: Viven la vida con intensidad. Pero su entusiasmo y energía pueden destruirlos. | D19: No | E19: No
A20: 19 | B20: Son como una centella que se fulmina a sí misma. | D20: No | E20: No
A21: 20 | B21: Suelen morir en forma súbita y a temprana edad. | D21: No | E21: No
A22: 21 | B22: No son impositivos ni manipuladores. Su liderazgo es por contagio. | D22: Si | E22: Si
... A29: 28 | B29: Excelentes en ocupaciones que requieran trato con multitudes, comunicación intensa y desparpajada animación. | D29: Si | E29: Si
B30: Porcentaje | C30: =COUNTIF(C2:C29,"si")/$A$29 -> 0 | D30: =COUNTIF(D2:D29,"si")/$A$29 -> 0.39285714 | E30: =COUNTIF(E2:E29,"si")/$A$29 -> 0.39285714 | F30: =COUNTIF(F2:F29,"si")/$A$29 -> 0

Sheet Resumen
B1: Tipología | C1: Niñez | D1: Norm. | E1: Adolescencia | F1: Norm. | G1: Juventud | H1: Norm. | I1: Vejez | J1: Norm. | L1: Índice de Carisma
A2: 1 | B2: Solitario | C2: =Solitario!C25 -> 0 | D2: =C2/$C$9 -> #DIV/0! | E2: =Solitario!D25 -> 0.17391304 | F2: =E2/$E$9 -> 0.047946325 | G2: =Solitario!E25 -> 0.17391304 | H2: =G2/$G$9 -> 0.047946325 | I2: =Solitario!F25 -> 0 | J2: =I2/$I$9 -> #DIV/0! | L2: 50-50 | M2: 1
A3: 2 | B3: Sensitivo | C3: =Sensitivo!C24 -> 0 | D3: =C3/$C$9 -> #DIV/0! | E3: =Sensitivo!D24 -> 0.59090909 | F3: =E3/$E$9 -> 0.16290854 | G3: =Sensitivo!E24 -> 0.59090909 | H3: =G3/$G$9 -> 0.16290854 | I3: =Sensitivo!F24 -> 0 | J3: =I3/$I$9 -> #DIV/0! | L3: 55-45 | M3: 0.9
A4: 3 | B4: Agudo | C4: =Agudo!C25 -> 0 | D4: =C4/$C$9 -> #DIV/0! | E4: =Agudo!D25 -> 0.82608696 | F4: =E4/$E$9 -> 0.22774504 | G4: =Agudo!E25 -> 0.82608696 | H4: =G4/$G$9 -> 0.22774504 | I4: =Agudo!F25 -> 0 | J4: =I4/$I$9 -> #DIV/0! | L4: 60-40 | M4: 0.8
A5: 4 | B5: Estructurado | C5: =Estructurado!C25 -> 0 | D5: =C5/$C$9 -> #DIV/0! | E5: =Estructurado!D25 -> 0.65217391 | F5: =E5/$E$9 -> 0.17979872 | G5: =Estructurado!E25 -> 0.65217391 | H5: =G5/$G$9 -> 0.17979872 | I5: =Estructurado!F25 -> 0 | J5: =I5/$I$9 -> #DIV/0! | L5: 65-35 | M5: 0.7
A6: 5 | B6: Energético | C6: =Energético!C25 -> 0 | D6: =C6/$C$9 -> #DIV/0! | E6: =Energético!D25 -> 0.39130435 | F6: =E6/$E$9 -> 0.10787923 | G6: =Energético!E25 -> 0.39130435 | H6: =G6/$G$9 -> 0.10787923 | I6: =Energético!F25 -> 0 | J6: =I6/$I$9 -> #DIV/0! | L6: 70-30 | M6: 0.6
A7: 6 | B7: Expansivo | C7: =Expansivo!C22 -> 0 | D7: =C7/$C$9 -> #DIV/0! | E7: =Expansivo!D22 -> 0.6 | F7: =E7/$E$9 -> 0.16541482 | G7: =Expansivo!E22 -> 0.6 | H7: =G7/$G$9 -> 0.16541482 | I7: =Expansivo!F22 -> 0 | J7: =I7/$I$9 -> #DIV/0! | L7: 75-25 | M7: 0.5
A8: 7 | B8: Carismático | C8: =Carismático!C30 -> 0 | D8: =C8/$C$9 -> #DIV/0! | E8: =Carismático!D30 -> 0.39285714 | F8: =E8/$E$9 -> 0.10830732 | G8: =Carismático!E30 -> 0.39285714 | H8: =G8/$G$9 -> 0.10830732 | I8: =Carismático!F30 -> 0 | J8: =I8/$I$9 -> #DIV/0! | L8: 80-20 | M8: 0.4
C9: =SUM(C2:C8) -> 0 | D9: =C9/$E$9 -> 0 | E9: =SUM(E2:E8) -> 3.6272445 | F9: =SUM(F2:F8) -> 1 | G9: =SUM(G2:G8) -> 3.6272445 | H9: =G9/$G$9 -> 1 | I9: =SUM(I2:I8) -> 0 | J9: =I9/$E$9 -> 0 | L9: 85-15 | M9: 0.3
E10: Agudo | F10: =F4/(F4+F8) -> 0.67770701 | L10: 90-10 | M10: 0.2
E11: Carismático | F11: =F8/(F4+F8) -> 0.32229299 | L11: 95-05 | M11: 0.1
E13: Agudo | F13: =F4/(F4+F5) -> 0.55882353 | G13: Agudo | H13: =H4/(H4+H5) -> 0.55882353
E14: Estructurado | F14: =F5/(F4+F5) -> 0.44117647 | G14: Estructurado | H14: =H5/(H4+H5) -> 0.44117647
E16: Indice de carisma | F16: 0 | G16: Indice de carisma | H16: =G28 -> 0.88
L17: Motriz | M17: Racional | N17: Enfasis Genético
F18: 0.7 | G18: =(1-F18)*2 -> 0.6 | L18: Agudo | M18: Estructurado | N18: Emocional
F19: 0.65 | G19: =(1-F19)*2 -> 0.7 | N19: Sensitivo
F20: 0.64 | G20: =(1-F20)*2 -> 0.72 | N20: Expansivo
F21: 0.63 | G21: =(1-F21)*2 -> 0.74
F22: 0.62 | G22: =(1-F22)*2 -> 0.76
F23: 0.61 | G23: =(1-F23)*2 -> 0.78
F24: 0.6 | G24: =(1-F24)*2 -> 0.8
F25: 0.59 | G25: =(1-F25)*2 -> 0.82
F26: 0.58 | G26: =(1-F26)*2 -> 0.84
F27: 0.57 | G27: =(1-F27)*2 -> 0.86
F28: 0.56 | G28: =(1-F28)*2 -> 0.88
F29: 0.55 | G29: =(1-F29)*2 -> 0.9
F30: 0.54 | G30: =(1-F30)*2 -> 0.92
F31: 0.53 | G31: =(1-F31)*2 -> 0.94
F32: 0.52 | G32: =(1-F32)*2 -> 0.96
... F34: 0.5 | G34: =(1-F34)*2 -> 1

Sheet Cartilla Fundamental
B2: Tipo: | C2: Activo
B3: Polaridad: | C3: Negativo
B4: Glándula maestra: | C4: Tiroides | D4: Agudo | E4: =Resumen!F13 -> 0.55882353
B5: Glándula subsidiaria: | C5: Pituitaria anterior | D5: Estructurado | E5: =Resumen!F14 -> 0.44117647
B6: Énfasis genético: | C6: Emocional
B7: Índice de carisma: | C7: =Resumen!H16 -> 0.88
B9: Dictum de autoafirmación: | C9: Yo gano
B10: Anhelo de plenitud de Ser: | C10: Reconocimiento
B11: Pecado capital: | C11: Envidia
B12: Virtud: | C12: Caridad
B13: Susceptibilidad: | C13: Crítica
B14: Rasgo dominante: | C14: Confusión
B16: Trabajo a realizar: | C16: Corrimientos a Estructurado,
C17: Equilibrio con los énfasis genéticos: Motriz y Racional
C18: Complementos con el resto de tipos del Heptagrama
